calaccess_raw/__init__.py
calaccess_raw/apps.py
calaccess_raw/fields.py
calaccess_raw/managers.py
calaccess_raw/admin/__init__.py
calaccess_raw/admin/base.py
calaccess_raw/admin/campaign.py
calaccess_raw/admin/common.py
calaccess_raw/admin/inactive.py
calaccess_raw/admin/lobbying.py
calaccess_raw/annotations/__init__.py
calaccess_raw/annotations/choices.py
calaccess_raw/annotations/documents.py
calaccess_raw/annotations/forms.csv
calaccess_raw/annotations/forms.py
calaccess_raw/annotations/sections.csv
calaccess_raw/management/__init__.py
calaccess_raw/management/commands/__init__.py
calaccess_raw/management/commands/cleancalaccessrawfile.py
calaccess_raw/management/commands/downloadcalaccessrawdata.py
calaccess_raw/management/commands/extractcalaccessrawfiles.py
calaccess_raw/management/commands/loadcalaccessrawfile.py
calaccess_raw/management/commands/updatecalaccessrawdata.py
calaccess_raw/migrations/0001_squashed_0014_auto_20160801_2039.py
calaccess_raw/migrations/0002_auto_20160802_2101.py
calaccess_raw/migrations/0003_auto_20160804_1443.py
calaccess_raw/migrations/0004_auto_20160804_1758.py
calaccess_raw/migrations/0005_auto_20160826_1449.py
calaccess_raw/migrations/0006_auto_20160826_2039.py
calaccess_raw/migrations/0007_auto_20160831_0132.py
calaccess_raw/migrations/0008_auto_20161025_1527.py
calaccess_raw/migrations/0009_auto_20161026_1641.py
calaccess_raw/migrations/0010_auto_20161026_1643.py
calaccess_raw/migrations/0011_auto_20161028_0129.py
calaccess_raw/migrations/0012_auto_20161123_2217.py
calaccess_raw/migrations/0013_auto_20161123_2219.py
calaccess_raw/migrations/0014_auto_20170421_1821.py
calaccess_raw/migrations/0015_auto_20170729_0218.py
calaccess_raw/migrations/0016_auto_20200818_0542.py
calaccess_raw/migrations/0017_auto_20210422_0047.py
calaccess_raw/migrations/0018_auto_20210426_2015.py
calaccess_raw/migrations/0019_alter_rawdataversion_download_zip_archive.py
calaccess_raw/migrations/0020_auto_20210614_1556.py
django_calaccess_raw_data-5.0.7.dist-info/LICENSE
django_calaccess_raw_data-5.0.7.dist-info/METADATA
django_calaccess_raw_data-5.0.7.dist-info/WHEEL
django_calaccess_raw_data-5.0.7.dist-info/top_level.txt
django_calaccess_raw_data-5.0.7.dist-info/RECORD
