Metadata-Version: 2.1
Name: django-calaccess-raw-data
Version: 5.0.7
Summary: A Django app to download, extract and load campaign finance and lobbying activity data from the California Secretary of State's CAL-ACCESS database
Home-page: http://django-calaccess.californiacivicdata.org/
Author: Ben Welsh
Author-email: b@palewi.re
License: MIT
Project-URL: Project, https://www.californiacivicdata.org/
Project-URL: Documentation, https://django-calaccess.californiacivicdata.org/
Project-URL: Funding, https://www.californiacivicdata.org/about/
Project-URL: Source, https://github.com/palewire/django-calaccess-raw-data
Project-URL: Testing, https://github.com/palewire/django-calaccess-raw-data/actions/workflows/tests.yaml
Project-URL: Tracker, https://github.com/palewire/django-calaccess-raw-data/issues
Classifier: Development Status :: 5 - Production/Stable
Classifier: Operating System :: OS Independent
Classifier: Intended Audience :: Developers
Classifier: Programming Language :: Python
Classifier: Programming Language :: Python :: 3
Classifier: Programming Language :: Python :: 3.8
Classifier: Programming Language :: Python :: 3.9
Classifier: Programming Language :: Python :: 3.10
Classifier: Framework :: Django
Classifier: Framework :: Django :: 4
Classifier: License :: OSI Approved :: MIT License
License-File: LICENSE
Requires-Dist: django ==4.0.*
Requires-Dist: django-postgres-copy
Requires-Dist: requests
Requires-Dist: csvkit
Requires-Dist: django-internetarchive-storage
